CHANGELOG.rst
LICENSE.txt
MANIFEST.in
README.rst
setup.cfg
setup.py
swaggerpy/__init__.py
swaggerpy/client.py
swaggerpy/codegen.py
swaggerpy/http_client.py
swaggerpy/processors.py
swaggerpy/swagger_model.py
swaggerpy.egg-info/PKG-INFO
swaggerpy.egg-info/SOURCES.txt
swaggerpy.egg-info/dependency_links.txt
swaggerpy.egg-info/entry_points.txt
swaggerpy.egg-info/requires.txt
swaggerpy.egg-info/top_level.txt