Metadata-Version: 1.1
Name: swaggerpy
Version: 0.2.0
Summary: Library for accessing Swagger-enabled API's
Home-page: https://github.com/digium/swagger-py
Author: Digium, Inc.
Author-email: dlee@digium.com
License: BSD 3-Clause License
Platform: UNKNOWN
Classifier: Development Status :: 1 - Planning
Classifier: Intended Audience :: Developers
Classifier: Topic :: Software Development :: Libraries :: Python Modules
Classifier: License :: OSI Approved :: BSD License
Classifier: Operating System :: OS Independent
Classifier: Programming Language :: Python
